crepobenchmark
