Metadata-Version: 1.2
Name: crepobenchmark
Version: 0.0.2
Summary: Benchmark for inference of credal networks.
Home-page: UNKNOWN
Author: Rafael Cabañas, Alessandro Antonucci
Author-email: rcabanas@idsia.ch, alessandro@antonucci.ch
License: GNU GPLv3
Keywords: credal networks
Platform: UNKNOWN
Classifier: Intended Audience :: Developers
Classifier: Intended Audience :: Education
Classifier: Intended Audience :: Science/Research
Classifier: License :: OSI Approved :: Apache Software License
Classifier: Operating System :: POSIX :: Linux
Classifier: Operating System :: MacOS :: MacOS X
Classifier: Operating System :: Microsoft :: Windows
Classifier: Programming Language :: Python :: 3.4
Requires-Python: >=3.5
